{
       "count_results": 6,
       "results": [
              {
                     "returned": {
                            "data": {
                                   "county_name": "",
                                   "counties_msa": "Houston County, MN; La Crosse County, WI; ",
                                   "town_name": "",
                                   "metro_status": "1",
                                   "metro_name": "La Crosse-Onalaska, WI-MN MSA",
                                   "area_name": "La Crosse-Onalaska, WI-MN MSA",
                                   "smallarea_status": "0",
                                   "basicdata": {
                                          "Efficiency": 516,
                                          "One-Bedroom": 612,
                                          "Two-Bedroom": 814,
                                          "Three-Bedroom": 1162,
                                          "Four-Bedroom": 1434,
                                          "year": "2017"
                                   }
                            }
                     }
              },
              {
                     "returned": {
                            "data": {
                                   "county_name": "",
                                   "counties_msa": "Houston County, MN; La Crosse County, WI; ",
                                   "town_name": "",
                                   "metro_status": "1",
                                   "metro_name": "La Crosse-Onalaska, WI-MN MSA",
                                   "area_name": "La Crosse-Onalaska, WI-MN MSA",
                                   "smallarea_status": "0",
                                   "basicdata": {
                                          "Efficiency": 506,
                                          "One-Bedroom": 596,
                                          "Two-Bedroom": 793,
                                          "Three-Bedroom": 1111,
                                          "Four-Bedroom": 1397,
                                          "year": "2018"
                                   }
                            }
                     }
              },
              {
                     "returned": {
                            "data": {
                                   "county_name": "",
                                   "counties_msa": "Houston County, MN; La Crosse County, WI; ",
                                   "town_name": "",
                                   "metro_status": "1",
                                   "metro_name": "La Crosse-Onalaska, WI-MN MSA",
                                   "area_name": "La Crosse-Onalaska, WI-MN MSA",
                                   "smallarea_status": "0",
                                   "basicdata": {
                                          "Efficiency": 531,
                                          "One-Bedroom": 624,
                                          "Two-Bedroom": 826,
                                          "Three-Bedroom": 1140,
                                          "Four-Bedroom": 1451,
                                          "year": "2019"
                                   }
                            }
                     }
              },
              {
                     "returned": {
                            "data": {
                                   "county_name": "",
                                   "counties_msa": "Houston County, MN; La Crosse County, WI; ",
                                   "town_name": "",
                                   "metro_status": "1",
                                   "metro_name": "La Crosse-Onalaska, WI-MN MSA",
                                   "area_name": "La Crosse-Onalaska, WI-MN MSA",
                                   "smallarea_status": "0",
                                   "basicdata": {
                                          "Efficiency": 540,
                                          "One-Bedroom": 629,
                                          "Two-Bedroom": 829,
                                          "Three-Bedroom": 1152,
                                          "Four-Bedroom": 1455,
                                          "year": "2020"
                                   }
                            }
                     }
              },
              {
                     "returned": {
                            "data": {
                                   "county_name": "",
                                   "counties_msa": "Houston County, MN; La Crosse County, WI; ",
                                   "town_name": "",
                                   "metro_status": "1",
                                   "metro_name": "La Crosse-Onalaska, WI-MN MSA",
                                   "area_name": "La Crosse-Onalaska, WI-MN MSA",
                                   "smallarea_status": "0",
                                   "basicdata": {
                                          "Efficiency": 577,
                                          "One-Bedroom": 673,
                                          "Two-Bedroom": 874,
                                          "Three-Bedroom": 1216,
                                          "Four-Bedroom": 1513,
                                          "year": "2021"
                                   }
                            }
                     }
              },
              {
                     "returned": {
                            "data": {
                                   "county_name": "",
                                   "counties_msa": "Houston County, MN; La Crosse County, WI; ",
                                   "town_name": "",
                                   "metro_status": "1",
                                   "metro_name": "La Crosse-Onalaska, WI-MN",
                                   "area_name": "La Crosse-Onalaska, WI-MN MSA",
                                   "smallarea_status": "0",
                                   "basicdata": {
                                          "Efficiency": 618,
                                          "One-Bedroom": 724,
                                          "Two-Bedroom": 930,
                                          "Three-Bedroom": 1300,
                                          "Four-Bedroom": 1592,
                                          "year": "2022"
                                   }
                            }
                     }
              }
       ]
}