{
       "count_results": 6,
       "results": [
              {
                     "returned": {
                            "data": {
                                   "county_name": "",
                                   "counties_msa": "Lee County, FL; ",
                                   "town_name": "",
                                   "metro_status": "1",
                                   "metro_name": "Cape Coral-Fort Myers, FL MSA",
                                   "area_name": "Cape Coral-Fort Myers, FL MSA",
                                   "smallarea_status": "0",
                                   "basicdata": {
                                          "Efficiency": 687,
                                          "One-Bedroom": 741,
                                          "Two-Bedroom": 920,
                                          "Three-Bedroom": 1194,
                                          "Four-Bedroom": 1331,
                                          "year": "2017"
                                   }
                            }
                     }
              },
              {
                     "returned": {
                            "data": {
                                   "county_name": "",
                                   "counties_msa": "Lee County, FL; ",
                                   "town_name": "",
                                   "metro_status": "1",
                                   "metro_name": "Cape Coral-Fort Myers, FL MSA",
                                   "area_name": "Cape Coral-Fort Myers, FL MSA",
                                   "smallarea_status": "0",
                                   "basicdata": {
                                          "Efficiency": 701,
                                          "One-Bedroom": 773,
                                          "Two-Bedroom": 956,
                                          "Three-Bedroom": 1240,
                                          "Four-Bedroom": 1415,
                                          "year": "2018"
                                   }
                            }
                     }
              },
              {
                     "returned": {
                            "data": {
                                   "county_name": "",
                                   "counties_msa": "Lee County, FL; ",
                                   "town_name": "",
                                   "metro_status": "1",
                                   "metro_name": "Cape Coral-Fort Myers, FL MSA",
                                   "area_name": "Cape Coral-Fort Myers, FL MSA",
                                   "smallarea_status": "0",
                                   "basicdata": {
                                          "Efficiency": 776,
                                          "One-Bedroom": 838,
                                          "Two-Bedroom": 1039,
                                          "Three-Bedroom": 1351,
                                          "Four-Bedroom": 1547,
                                          "year": "2019"
                                   }
                            }
                     }
              },
              {
                     "returned": {
                            "data": {
                                   "county_name": "",
                                   "counties_msa": "Lee County, FL; ",
                                   "town_name": "",
                                   "metro_status": "1",
                                   "metro_name": "Cape Coral-Fort Myers, FL MSA",
                                   "area_name": "Cape Coral-Fort Myers, FL MSA",
                                   "smallarea_status": "0",
                                   "basicdata": {
                                          "Efficiency": 875,
                                          "One-Bedroom": 946,
                                          "Two-Bedroom": 1182,
                                          "Three-Bedroom": 1540,
                                          "Four-Bedroom": 1752,
                                          "year": "2020"
                                   }
                            }
                     }
              },
              {
                     "returned": {
                            "data": {
                                   "county_name": "",
                                   "counties_msa": "Lee County, FL; ",
                                   "town_name": "",
                                   "metro_status": "1",
                                   "metro_name": "Cape Coral-Fort Myers, FL MSA",
                                   "area_name": "Cape Coral-Fort Myers, FL MSA",
                                   "smallarea_status": "0",
                                   "basicdata": {
                                          "Efficiency": 931,
                                          "One-Bedroom": 951,
                                          "Two-Bedroom": 1197,
                                          "Three-Bedroom": 1559,
                                          "Four-Bedroom": 1762,
                                          "year": "2021"
                                   }
                            }
                     }
              },
              {
                     "returned": {
                            "data": {
                                   "county_name": "",
                                   "counties_msa": "Lee County, FL; ",
                                   "town_name": "",
                                   "metro_status": "1",
                                   "metro_name": "Cape Coral-Fort Myers, FL",
                                   "area_name": "Cape Coral-Fort Myers, FL MSA",
                                   "smallarea_status": "0",
                                   "basicdata": {
                                          "Efficiency": 976,
                                          "One-Bedroom": 979,
                                          "Two-Bedroom": 1231,
                                          "Three-Bedroom": 1603,
                                          "Four-Bedroom": 1820,
                                          "year": "2022"
                                   }
                            }
                     }
              }
       ]
}