{
       "responses": {
              "fmr": [
                     {
                            "county_name": "Middlesex County, CT",
                            "counties_msa": "",
                            "town_name": "Clinton town",
                            "metro_status": "1",
                            "metro_name": "Hartford-West Hartford-East Hartford, CT MSA",
                            "area_name": "Southern Middlesex County, CT HUD Metro FMR Area",
                            "smallarea_status": "0",
                            "basicdata": {
                                   "Efficiency": 886,
                                   "One-Bedroom": 1029,
                                   "Two-Bedroom": 1367,
                                   "Three-Bedroom": 1990,
                                   "Four-Bedroom": 2051,
                                   "year": "2017"
                            }
                     },
                     {
                            "county_name": "Middlesex County, CT",
                            "counties_msa": "",
                            "town_name": "Clinton town",
                            "metro_status": "1",
                            "metro_name": "Hartford-West Hartford-East Hartford, CT MSA",
                            "area_name": "Southern Middlesex County, CT HUD Metro FMR Area",
                            "smallarea_status": "0",
                            "basicdata": {
                                   "Efficiency": 884,
                                   "One-Bedroom": 1042,
                                   "Two-Bedroom": 1386,
                                   "Three-Bedroom": 2016,
                                   "Four-Bedroom": 2441,
                                   "year": "2018"
                            }
                     },
                     {
                            "county_name": "Middlesex County, CT",
                            "counties_msa": "",
                            "town_name": "Clinton town",
                            "metro_status": "1",
                            "metro_name": "Hartford-West Hartford-East Hartford, CT MSA",
                            "area_name": "Southern Middlesex County, CT HUD Metro FMR Area",
                            "smallarea_status": "0",
                            "basicdata": {
                                   "Efficiency": 917,
                                   "One-Bedroom": 1079,
                                   "Two-Bedroom": 1427,
                                   "Three-Bedroom": 2063,
                                   "Four-Bedroom": 2506,
                                   "year": "2019"
                            }
                     },
                     {
                            "county_name": "Middlesex County, CT",
                            "counties_msa": "",
                            "town_name": "Clinton town",
                            "metro_status": "1",
                            "metro_name": "Hartford-West Hartford-East Hartford, CT MSA",
                            "area_name": "Southern Middlesex County, CT HUD Metro FMR Area",
                            "smallarea_status": "0",
                            "basicdata": {
                                   "Efficiency": 944,
                                   "One-Bedroom": 1100,
                                   "Two-Bedroom": 1449,
                                   "Three-Bedroom": 2090,
                                   "Four-Bedroom": 2544,
                                   "year": "2020"
                            }
                     },
                     {
                            "county_name": "Middlesex County, CT",
                            "counties_msa": "",
                            "town_name": "Clinton town",
                            "metro_status": "1",
                            "metro_name": "Hartford-West Hartford-East Hartford, CT MSA",
                            "area_name": "Southern Middlesex County, CT HUD Metro FMR Area",
                            "smallarea_status": "0",
                            "basicdata": {
                                   "Efficiency": 1004,
                                   "One-Bedroom": 1155,
                                   "Two-Bedroom": 1522,
                                   "Three-Bedroom": 2178,
                                   "Four-Bedroom": 2635,
                                   "year": "2021"
                            }
                     },
                     {
                            "county_name": "Middlesex County, CT",
                            "counties_msa": "",
                            "town_name": "Clinton town",
                            "metro_status": "1",
                            "metro_name": "Hartford-East Hartford-Middletown, CT",
                            "area_name": "Southern Middlesex County, CT HUD Metro FMR Area",
                            "smallarea_status": "0",
                            "basicdata": {
                                   "Efficiency": 957,
                                   "One-Bedroom": 1101,
                                   "Two-Bedroom": 1441,
                                   "Three-Bedroom": 2047,
                                   "Four-Bedroom": 2466,
                                   "year": "2022"
                            }
                     }
              ],
              "il": [
                     {
                            "county_name": "Middlesex County, CT",
                            "counties_msa": "",
                            "town_name": "Clinton town",
                            "metro_status": "1",
                            "metro_name": "Hartford-West Hartford-East Hartford, CT MSA",
                            "area_name": "Southern Middlesex County, CT HUD Metro FMR Area",
                            "year": "2017",
                            "median_income": 106200,
                            "very_low": {
                                   "il50_p1": 37200,
                                   "il50_p2": 42500,
                                   "il50_p3": 47800,
                                   "il50_p4": 53100,
                                   "il50_p5": 57350,
                                   "il50_p6": 61600,
                                   "il50_p7": 65850,
                                   "il50_p8": 70100
                            },
                            "extremely_low": {
                                   "il30_p1": 22300,
                                   "il30_p2": 25500,
                                   "il30_p3": 28700,
                                   "il30_p4": 31850,
                                   "il30_p5": 34400,
                                   "il30_p6": 36950,
                                   "il30_p7": 39500,
                                   "il30_p8": 42050
                            },
                            "low": {
                                   "il80_p1": 47600,
                                   "il80_p2": 54400,
                                   "il80_p3": 61200,
                                   "il80_p4": 68000,
                                   "il80_p5": 73450,
                                   "il80_p6": 78900,
                                   "il80_p7": 84350,
                                   "il80_p8": 89800
                            }
                     },
                     {
                            "county_name": "Middlesex County, CT",
                            "counties_msa": "",
                            "town_name": "Clinton town",
                            "metro_status": "1",
                            "metro_name": "Hartford-West Hartford-East Hartford, CT MSA",
                            "area_name": "Southern Middlesex County, CT HUD Metro FMR Area",
                            "year": "2018",
                            "median_income": 108500,
                            "very_low": {
                                   "il50_p1": 38000,
                                   "il50_p2": 43400,
                                   "il50_p3": 48850,
                                   "il50_p4": 54250,
                                   "il50_p5": 58600,
                                   "il50_p6": 62950,
                                   "il50_p7": 67300,
                                   "il50_p8": 71650
                            },
                            "extremely_low": {
                                   "il30_p1": 22800,
                                   "il30_p2": 26050,
                                   "il30_p3": 29300,
                                   "il30_p4": 32550,
                                   "il30_p5": 35200,
                                   "il30_p6": 37800,
                                   "il30_p7": 40400,
                                   "il30_p8": 43000
                            },
                            "low": {
                                   "il80_p1": 50350,
                                   "il80_p2": 57550,
                                   "il80_p3": 64750,
                                   "il80_p4": 71900,
                                   "il80_p5": 77700,
                                   "il80_p6": 83450,
                                   "il80_p7": 89200,
                                   "il80_p8": 94950
                            }
                     },
                     {
                            "county_name": "Middlesex County, CT",
                            "counties_msa": "",
                            "town_name": "Clinton town",
                            "metro_status": "1",
                            "metro_name": "Hartford-West Hartford-East Hartford, CT MSA",
                            "area_name": "Southern Middlesex County, CT HUD Metro FMR Area",
                            "year": "2019",
                            "median_income": 110900,
                            "very_low": {
                                   "il50_p1": 38850,
                                   "il50_p2": 44400,
                                   "il50_p3": 49950,
                                   "il50_p4": 55450,
                                   "il50_p5": 59900,
                                   "il50_p6": 64350,
                                   "il50_p7": 68800,
                                   "il50_p8": 73200
                            },
                            "extremely_low": {
                                   "il30_p1": 23300,
                                   "il30_p2": 26600,
                                   "il30_p3": 29950,
                                   "il30_p4": 33250,
                                   "il30_p5": 35950,
                                   "il30_p6": 38600,
                                   "il30_p7": 41250,
                                   "il30_p8": 43900
                            },
                            "low": {
                                   "il80_p1": 52850,
                                   "il80_p2": 60400,
                                   "il80_p3": 67950,
                                   "il80_p4": 75500,
                                   "il80_p5": 81550,
                                   "il80_p6": 87600,
                                   "il80_p7": 93650,
                                   "il80_p8": 99700
                            }
                     },
                     {
                            "county_name": "Middlesex County, CT",
                            "counties_msa": "",
                            "town_name": "Clinton town",
                            "metro_status": "1",
                            "metro_name": "Hartford-West Hartford-East Hartford, CT MSA",
                            "area_name": "Southern Middlesex County, CT HUD Metro FMR Area",
                            "year": "2020",
                            "median_income": 112000,
                            "very_low": {
                                   "il50_p1": 39200,
                                   "il50_p2": 44800,
                                   "il50_p3": 50400,
                                   "il50_p4": 56000,
                                   "il50_p5": 60500,
                                   "il50_p6": 65000,
                                   "il50_p7": 69450,
                                   "il50_p8": 73950
                            },
                            "extremely_low": {
                                   "il30_p1": 23550,
                                   "il30_p2": 26900,
                                   "il30_p3": 30250,
                                   "il30_p4": 33600,
                                   "il30_p5": 36300,
                                   "il30_p6": 39000,
                                   "il30_p7": 41700,
                                   "il30_p8": 44400
                            },
                            "low": {
                                   "il80_p1": 54950,
                                   "il80_p2": 62800,
                                   "il80_p3": 70650,
                                   "il80_p4": 78500,
                                   "il80_p5": 84800,
                                   "il80_p6": 91100,
                                   "il80_p7": 97350,
                                   "il80_p8": 103650
                            }
                     },
                     {
                            "county_name": "Middlesex County, CT",
                            "counties_msa": "",
                            "town_name": "Clinton town",
                            "metro_status": "1",
                            "metro_name": "Hartford-West Hartford-East Hartford, CT MSA",
                            "area_name": "Southern Middlesex County, CT HUD Metro FMR Area",
                            "year": "2021",
                            "median_income": 114600,
                            "very_low": {
                                   "il50_p1": 40150,
                                   "il50_p2": 45850,
                                   "il50_p3": 51600,
                                   "il50_p4": 57300,
                                   "il50_p5": 61900,
                                   "il50_p6": 66500,
                                   "il50_p7": 71100,
                                   "il50_p8": 75650
                            },
                            "extremely_low": {
                                   "il30_p1": 24100,
                                   "il30_p2": 27550,
                                   "il30_p3": 31000,
                                   "il30_p4": 34400,
                                   "il30_p5": 37200,
                                   "il30_p6": 39950,
                                   "il30_p7": 42700,
                                   "il30_p8": 45450
                            },
                            "low": {
                                   "il80_p1": 55950,
                                   "il80_p2": 63950,
                                   "il80_p3": 71950,
                                   "il80_p4": 79900,
                                   "il80_p5": 86300,
                                   "il80_p6": 92700,
                                   "il80_p7": 99100,
                                   "il80_p8": 105500
                            }
                     },
                     {
                            "county_name": "Middlesex County, CT",
                            "counties_msa": "",
                            "town_name": "Clinton town",
                            "metro_status": "1",
                            "metro_name": "Hartford-East Hartford-Middletown, CT",
                            "area_name": "Southern Middlesex County, CT HUD Metro FMR Area",
                            "year": "2022",
                            "median_income": 124900,
                            "very_low": {
                                   "il50_p1": 43750,
                                   "il50_p2": 50000,
                                   "il50_p3": 56250,
                                   "il50_p4": 62450,
                                   "il50_p5": 67450,
                                   "il50_p6": 72450,
                                   "il50_p7": 77450,
                                   "il50_p8": 82450
                            },
                            "extremely_low": {
                                   "il30_p1": 26250,
                                   "il30_p2": 30000,
                                   "il30_p3": 33750,
                                   "il30_p4": 37450,
                                   "il30_p5": 40450,
                                   "il30_p6": 43450,
                                   "il30_p7": 46450,
                                   "il30_p8": 49450
                            },
                            "low": {
                                   "il80_p1": 62600,
                                   "il80_p2": 71550,
                                   "il80_p3": 80500,
                                   "il80_p4": 89400,
                                   "il80_p5": 96600,
                                   "il80_p6": 103750,
                                   "il80_p7": 110900,
                                   "il80_p8": 118050
                            }
                     }
              ]
       }
}